busywork/__init__.py
busywork/__main__.py
busywork/ci.py
busywork/install.py
busywork/pyproject.py
busywork/utils.py
busywork-0.1.0b2.dist-info/LICENSE
busywork-0.1.0b2.dist-info/METADATA
busywork-0.1.0b2.dist-info/WHEEL
busywork-0.1.0b2.dist-info/entry_points.txt
busywork-0.1.0b2.dist-info/top_level.txt
busywork-0.1.0b2.dist-info/RECORD
