Metadata-Version: 2.1
Name: busywork
Version: 0.1.0b2
Summary: A package for managing dependency groups.
License: GPL-v2
Project-URL: Repository, https://github.com/Lunarmagpie/busywork
Classifier: Programming Language :: Python :: 3
Requires-Python: >=3.9
License-File: LICENSE
Requires-Dist: pip
Requires-Dist: tomli (>=2.0.0)
Requires-Dist: dahlia (>=2.1.3)
Requires-Dist: unearth (>=0.6.2)
Requires-Dist: build (>=0.9.0)
Requires-Dist: installer (>=0.5.1)
Requires-Dist: packaging (>=21.3)
Requires-Dist: requests
